terraform_ai_py/ai.py
terraform_ai_py/cli.py
terraform_ai_py/main.py
terraform_ai_py/prompts.py
terraform_ai_py-0.1.1.dist-info/licenses/LICENSE
terraform_ai_py-0.1.1.dist-info/METADATA
terraform_ai_py-0.1.1.dist-info/WHEEL
terraform_ai_py-0.1.1.dist-info/entry_points.txt
terraform_ai_py-0.1.1.dist-info/top_level.txt
terraform_ai_py-0.1.1.dist-info/RECORD
