Metadata-Version: 2.4
Name: terraform-ai-py
Version: 0.1.1
Summary: AI-enhanced CLI tool for Terraform insights
Author-email: Emerson Silva <araujo.emerson28@gmail.com>
License-Expression: MIT
Requires-Python: >=3.8
License-File: LICENSE
Requires-Dist: openai
Requires-Dist: requests
Requires-Dist: python-dotenv
Dynamic: license-file
